{
  "LXSL13689": {
    "en_description_full": "",
    "es_description_full": "",
    "highlights": [],
    "es_title_optimized": "",
    "en_title_optimized": "",
    "descr_en": "",
    "descr_es": ""
  },
  "LXEL13690": {
    "en_description_full": "",
    "es_description_full": "",
    "highlights": [],
    "es_title_optimized": "",
    "en_title_optimized": "",
    "descr_en": "",
    "descr_es": ""
  },
  "LXGC14125": {
    "en_description_full": "",
    "es_description_full": "",
    "highlights": [],
    "es_title_optimized": "",
    "en_title_optimized": "",
    "descr_en": "",
    "descr_es": ""
  },
  "LXSR13635": {
    "en_description_full": "",
    "es_description_full": "",
    "highlights": [],
    "es_title_optimized": "",
    "en_title_optimized": "",
    "descr_en": "",
    "descr_es": ""
  },
  "LXEL13694": {
    "en_description_full": "",
    "es_description_full": "",
    "highlights": [],
    "es_title_optimized": "",
    "en_title_optimized": "",
    "descr_en": "",
    "descr_es": ""
  },
  "LXSF13753": {
    "en_description_full": "",
    "es_description_full": "",
    "highlights": [],
    "es_title_optimized": "",
    "en_title_optimized": "",
    "descr_en": "",
    "descr_es": ""
  },
  "LXER13634": {
    "en_description_full": "",
    "es_description_full": "",
    "highlights": [],
    "es_title_optimized": "",
    "en_title_optimized": "",
    "descr_en": "",
    "descr_es": ""
  },
  "LXPR13880": {
    "en_description_full": "",
    "es_description_full": "",
    "highlights": [],
    "es_title_optimized": "",
    "en_title_optimized": "",
    "descr_en": "",
    "descr_es": ""
  },
  "LXAR13844": {
    "en_description_full": "",
    "es_description_full": "",
    "highlights": [],
    "es_title_optimized": "",
    "en_title_optimized": "",
    "descr_en": "",
    "descr_es": ""
  },
  "LXAR13746": {
    "en_description_full": "",
    "es_description_full": "",
    "highlights": [],
    "es_title_optimized": "",
    "en_title_optimized": "",
    "descr_en": "",
    "descr_es": ""
  },
  "LXAR14101": {
    "en_description_full": "",
    "es_description_full": "",
    "highlights": [],
    "es_title_optimized": "",
    "en_title_optimized": "",
    "descr_en": "",
    "descr_es": ""
  },
  "LXPL13961": {
    "en_description_full": "",
    "es_description_full": "",
    "highlights": [],
    "es_title_optimized": "",
    "en_title_optimized": "",
    "descr_en": "",
    "descr_es": ""
  },
  "LXER10941": {
    "en_description_full": "",
    "es_description_full": "",
    "highlights": [],
    "es_title_optimized": "",
    "en_title_optimized": "",
    "descr_en": "",
    "descr_es": ""
  },
  "LXPR13877": {
    "en_description_full": "",
    "es_description_full": "",
    "highlights": [],
    "es_title_optimized": "",
    "en_title_optimized": "",
    "descr_en": "",
    "descr_es": ""
  },
  "LXSL13691": {
    "en_description_full": "",
    "es_description_full": "",
    "highlights": [],
    "es_title_optimized": "",
    "en_title_optimized": "",
    "descr_en": "",
    "descr_es": ""
  },
  "LXPR13766": {
    "en_description_full": "",
    "es_description_full": "",
    "highlights": [],
    "es_title_optimized": "",
    "en_title_optimized": "",
    "descr_en": "",
    "descr_es": ""
  },
  "LXHR12911": {
    "en_description_full": "",
    "es_description_full": "",
    "highlights": [],
    "es_title_optimized": "",
    "en_title_optimized": "",
    "descr_en": "",
    "descr_es": ""
  },
  "LXPR13875": {
    "en_description_full": "",
    "es_description_full": "",
    "highlights": [],
    "es_title_optimized": "",
    "en_title_optimized": "",
    "descr_en": "",
    "descr_es": ""
  },
  "LXPR13874": {
    "en_description_full": "",
    "es_description_full": "",
    "highlights": [],
    "es_title_optimized": "",
    "en_title_optimized": "",
    "descr_en": "",
    "descr_es": ""
  },
  "LXAC13758": {
    "en_description_full": "",
    "es_description_full": "",
    "highlights": [],
    "es_title_optimized": "",
    "en_title_optimized": "",
    "descr_en": "",
    "descr_es": ""
  },
  "LXCR13387": {
    "en_description_full": "",
    "es_description_full": "",
    "highlights": [],
    "es_title_optimized": "",
    "en_title_optimized": "",
    "descr_en": "",
    "descr_es": ""
  },
  "LXSR13699": {
    "en_description_full": "",
    "es_description_full": "",
    "highlights": [],
    "es_title_optimized": "",
    "en_title_optimized": "",
    "descr_en": "",
    "descr_es": ""
  },
  "LXER13704": {
    "en_description_full": "",
    "es_description_full": "",
    "highlights": [],
    "es_title_optimized": "",
    "en_title_optimized": "",
    "descr_en": "",
    "descr_es": ""
  },
  "LXSR14003": {
    "en_description_full": "",
    "es_description_full": "",
    "highlights": [],
    "es_title_optimized": "",
    "en_title_optimized": "",
    "descr_en": "",
    "descr_es": ""
  },
  "LXER24165": {
    "en_description_full": "",
    "es_description_full": "",
    "highlights": [],
    "es_title_optimized": "",
    "en_title_optimized": "",
    "descr_en": "",
    "descr_es": ""
  },
  "LXER23981": {
    "en_description_full": "",
    "es_description_full": "",
    "highlights": [],
    "es_title_optimized": "",
    "en_title_optimized": "",
    "descr_en": "",
    "descr_es": ""
  },
  "LXER24041": {
    "en_description_full": "",
    "es_description_full": "",
    "highlights": [],
    "es_title_optimized": "",
    "en_title_optimized": "",
    "descr_en": "",
    "descr_es": ""
  },
  "LXER22953": {
    "en_description_full": "",
    "es_description_full": "",
    "highlights": [],
    "es_title_optimized": "",
    "en_title_optimized": "",
    "descr_en": "",
    "descr_es": ""
  },
  "LXER24032": {
    "en_description_full": "",
    "es_description_full": "",
    "highlights": [],
    "es_title_optimized": "",
    "en_title_optimized": "",
    "descr_en": "",
    "descr_es": ""
  },
  "LXER20783": {
    "en_description_full": "",
    "es_description_full": "",
    "highlights": [],
    "es_title_optimized": "",
    "en_title_optimized": "",
    "descr_en": "",
    "descr_es": ""
  },
  "LXER23701": {
    "en_description_full": "",
    "es_description_full": "",
    "highlights": [],
    "es_title_optimized": "",
    "en_title_optimized": "",
    "descr_en": "",
    "descr_es": ""
  },
  "LXER20784": {
    "en_description_full": "",
    "es_description_full": "",
    "highlights": [],
    "es_title_optimized": "",
    "en_title_optimized": "",
    "descr_en": "",
    "descr_es": ""
  },
  "LXER23616": {
    "en_description_full": "",
    "es_description_full": "",
    "highlights": [],
    "es_title_optimized": "",
    "en_title_optimized": "",
    "descr_en": "",
    "descr_es": ""
  },
  "LXER20782": {
    "en_description_full": "",
    "es_description_full": "",
    "highlights": [],
    "es_title_optimized": "",
    "en_title_optimized": "",
    "descr_en": "",
    "descr_es": ""
  },
  "LXER23725": {
    "en_description_full": "",
    "es_description_full": "",
    "highlights": [],
    "es_title_optimized": "",
    "en_title_optimized": "",
    "descr_en": "",
    "descr_es": ""
  },
  "LXER22738": {
    "en_description_full": "",
    "es_description_full": "",
    "highlights": [],
    "es_title_optimized": "",
    "en_title_optimized": "",
    "descr_en": "",
    "descr_es": ""
  },
  "LXER22958": {
    "en_description_full": "",
    "es_description_full": "",
    "highlights": [],
    "es_title_optimized": "",
    "en_title_optimized": "",
    "descr_en": "",
    "descr_es": ""
  },
  "LXER22869": {
    "en_description_full": "",
    "es_description_full": "",
    "highlights": [],
    "es_title_optimized": "",
    "en_title_optimized": "",
    "descr_en": "",
    "descr_es": ""
  },
  "LXCR23597": {
    "en_description_full": "",
    "es_description_full": "",
    "highlights": [],
    "es_title_optimized": "",
    "en_title_optimized": "",
    "descr_en": "",
    "descr_es": ""
  },
  "LXER20083": {
    "en_description_full": "",
    "es_description_full": "",
    "highlights": [],
    "es_title_optimized": "",
    "en_title_optimized": "",
    "descr_en": "",
    "descr_es": ""
  },
  "LXCR24160": {
    "en_description_full": "",
    "es_description_full": "",
    "highlights": [],
    "es_title_optimized": "",
    "en_title_optimized": "",
    "descr_en": "",
    "descr_es": ""
  },
  "LXSC13809": {
    "en_description_full": "",
    "es_description_full": "",
    "highlights": [],
    "es_title_optimized": "",
    "en_title_optimized": "",
    "descr_en": "",
    "descr_es": ""
  },
  "LXER13430": {
    "en_description_full": "",
    "es_description_full": "",
    "highlights": [],
    "es_title_optimized": "",
    "en_title_optimized": "",
    "descr_en": "",
    "descr_es": ""
  },
  "LXSR14126": {
    "en_description_full": "",
    "es_description_full": "",
    "highlights": [],
    "es_title_optimized": "",
    "en_title_optimized": "",
    "descr_en": "",
    "descr_es": ""
  },
  "LXER13873": {
    "en_description_full": "",
    "es_description_full": "",
    "highlights": [],
    "es_title_optimized": "",
    "en_title_optimized": "",
    "descr_en": "",
    "descr_es": ""
  },
  "LXER13703": {
    "en_description_full": "",
    "es_description_full": "",
    "highlights": [],
    "es_title_optimized": "",
    "en_title_optimized": "",
    "descr_en": "",
    "descr_es": ""
  },
  "LXSR13693": {
    "en_description_full": "",
    "es_description_full": "",
    "highlights": [],
    "es_title_optimized": "",
    "en_title_optimized": "",
    "descr_en": "",
    "descr_es": ""
  },
  "LXER13406": {
    "en_description_full": "",
    "es_description_full": "",
    "highlights": [],
    "es_title_optimized": "",
    "en_title_optimized": "",
    "descr_en": "",
    "descr_es": ""
  },
  "LXCR13973": {
    "en_description_full": "",
    "es_description_full": "",
    "highlights": [],
    "es_title_optimized": "",
    "en_title_optimized": "",
    "descr_en": "",
    "descr_es": ""
  },
  "LXCR13200": {
    "en_description_full": "",
    "es_description_full": "",
    "highlights": [],
    "es_title_optimized": "",
    "en_title_optimized": "",
    "descr_en": "",
    "descr_es": ""
  },
  "LXCR14142": {
    "en_description_full": "",
    "es_description_full": "",
    "highlights": [],
    "es_title_optimized": "",
    "en_title_optimized": "",
    "descr_en": "",
    "descr_es": ""
  },
  "LXER12894": {
    "en_description_full": "",
    "es_description_full": "",
    "highlights": [],
    "es_title_optimized": "",
    "en_title_optimized": "",
    "descr_en": "",
    "descr_es": ""
  },
  "LXER13507": {
    "en_description_full": "",
    "es_description_full": "",
    "highlights": [],
    "es_title_optimized": "",
    "en_title_optimized": "",
    "descr_en": "",
    "descr_es": ""
  },
  "LXER14115": {
    "en_description_full": "",
    "es_description_full": "",
    "highlights": [],
    "es_title_optimized": "",
    "en_title_optimized": "",
    "descr_en": "",
    "descr_es": ""
  },
  "LXHR13063": {
    "en_description_full": "",
    "es_description_full": "",
    "highlights": [],
    "es_title_optimized": "",
    "en_title_optimized": "",
    "descr_en": "",
    "descr_es": ""
  },
  "LXER13612": {
    "en_description_full": "",
    "es_description_full": "",
    "highlights": [],
    "es_title_optimized": "",
    "en_title_optimized": "",
    "descr_en": "",
    "descr_es": ""
  },
  "LXER13557": {
    "en_description_full": "",
    "es_description_full": "",
    "highlights": [],
    "es_title_optimized": "",
    "en_title_optimized": "",
    "descr_en": "",
    "descr_es": ""
  },
  "LXER12500": {
    "en_description_full": "",
    "es_description_full": "",
    "highlights": [],
    "es_title_optimized": "",
    "en_title_optimized": "",
    "descr_en": "",
    "descr_es": ""
  },
  "LXPR13516": {
    "en_description_full": "",
    "es_description_full": "",
    "highlights": [],
    "es_title_optimized": "",
    "en_title_optimized": "",
    "descr_en": "",
    "descr_es": ""
  },
  "LXER12600": {
    "en_description_full": "",
    "es_description_full": "",
    "highlights": [],
    "es_title_optimized": "",
    "en_title_optimized": "",
    "descr_en": "",
    "descr_es": ""
  },
  "LXER14092": {
    "en_description_full": "",
    "es_description_full": "",
    "highlights": [],
    "es_title_optimized": "",
    "en_title_optimized": "",
    "descr_en": "",
    "descr_es": ""
  },
  "LXER13172": {
    "en_description_full": "",
    "es_description_full": "",
    "highlights": [],
    "es_title_optimized": "",
    "en_title_optimized": "",
    "descr_en": "",
    "descr_es": ""
  },
  "LXHR12502": {
    "en_description_full": "",
    "es_description_full": "",
    "highlights": [],
    "es_title_optimized": "",
    "en_title_optimized": "",
    "descr_en": "",
    "descr_es": ""
  },
  "LXSR14097": {
    "en_description_full": "",
    "es_description_full": "",
    "highlights": [],
    "es_title_optimized": "",
    "en_title_optimized": "",
    "descr_en": "",
    "descr_es": ""
  },
  "LXCR10614": {
    "en_description_full": "",
    "es_description_full": "",
    "highlights": [],
    "es_title_optimized": "",
    "en_title_optimized": "",
    "descr_en": "",
    "descr_es": ""
  },
  "LXER13448": {
    "en_description_full": "",
    "es_description_full": "",
    "highlights": [],
    "es_title_optimized": "",
    "en_title_optimized": "",
    "descr_en": "",
    "descr_es": ""
  },
  "LXAR13889": {
    "en_description_full": "",
    "es_description_full": "",
    "highlights": [],
    "es_title_optimized": "",
    "en_title_optimized": "",
    "descr_en": "",
    "descr_es": ""
  },
  "LXPR12832": {
    "en_description_full": "",
    "es_description_full": "",
    "highlights": [],
    "es_title_optimized": "",
    "en_title_optimized": "",
    "descr_en": "",
    "descr_es": ""
  },
  "LXER10575": {
    "en_description_full": "",
    "es_description_full": "",
    "highlights": [],
    "es_title_optimized": "",
    "en_title_optimized": "",
    "descr_en": "",
    "descr_es": ""
  },
  "LXER12714": {
    "en_description_full": "",
    "es_description_full": "",
    "highlights": [],
    "es_title_optimized": "",
    "en_title_optimized": "",
    "descr_en": "",
    "descr_es": ""
  },
  "LXCR12826": {
    "en_description_full": "",
    "es_description_full": "",
    "highlights": [],
    "es_title_optimized": "",
    "en_title_optimized": "",
    "descr_en": "",
    "descr_es": ""
  },
  "LXER13952": {
    "en_description_full": "",
    "es_description_full": "",
    "highlights": [],
    "es_title_optimized": "",
    "en_title_optimized": "",
    "descr_en": "",
    "descr_es": ""
  },
  "LXPR13603": {
    "en_description_full": "",
    "es_description_full": "",
    "highlights": [],
    "es_title_optimized": "",
    "en_title_optimized": "",
    "descr_en": "",
    "descr_es": ""
  },
  "LXSR14052": {
    "en_description_full": "",
    "es_description_full": "",
    "highlights": [],
    "es_title_optimized": "",
    "en_title_optimized": "",
    "descr_en": "",
    "descr_es": ""
  },
  "LXER13776": {
    "en_description_full": "",
    "es_description_full": "",
    "highlights": [],
    "es_title_optimized": "",
    "en_title_optimized": "",
    "descr_en": "",
    "descr_es": ""
  },
  "LXER12640": {
    "en_description_full": "",
    "es_description_full": "",
    "highlights": [],
    "es_title_optimized": "",
    "en_title_optimized": "",
    "descr_en": "",
    "descr_es": ""
  },
  "LXER11012": {
    "en_description_full": "",
    "es_description_full": "",
    "highlights": [],
    "es_title_optimized": "",
    "en_title_optimized": "",
    "descr_en": "",
    "descr_es": ""
  },
  "LXCR12882": {
    "en_description_full": "",
    "es_description_full": "",
    "highlights": [],
    "es_title_optimized": "",
    "en_title_optimized": "",
    "descr_en": "",
    "descr_es": ""
  },
  "LXCR12730": {
    "en_description_full": "",
    "es_description_full": "",
    "highlights": [],
    "es_title_optimized": "",
    "en_title_optimized": "",
    "descr_en": "",
    "descr_es": ""
  },
  "LXHR11130": {
    "en_description_full": "",
    "es_description_full": "",
    "highlights": [],
    "es_title_optimized": "",
    "en_title_optimized": "",
    "descr_en": "",
    "descr_es": ""
  },
  "LXSR13830": {
    "en_description_full": "",
    "es_description_full": "",
    "highlights": [],
    "es_title_optimized": "",
    "en_title_optimized": "",
    "descr_en": "",
    "descr_es": ""
  },
  "LXER13429": {
    "en_description_full": "",
    "es_description_full": "",
    "highlights": [],
    "es_title_optimized": "",
    "en_title_optimized": "",
    "descr_en": "",
    "descr_es": ""
  },
  "LXER13237": {
    "en_description_full": "",
    "es_description_full": "",
    "highlights": [],
    "es_title_optimized": "",
    "en_title_optimized": "",
    "descr_en": "",
    "descr_es": ""
  },
  "LXER11150": {
    "en_description_full": "",
    "es_description_full": "",
    "highlights": [],
    "es_title_optimized": "",
    "en_title_optimized": "",
    "descr_en": "",
    "descr_es": ""
  },
  "LXSR13637": {
    "en_description_full": "",
    "es_description_full": "",
    "highlights": [],
    "es_title_optimized": "",
    "en_title_optimized": "",
    "descr_en": "",
    "descr_es": ""
  },
  "LXER10103": {
    "en_description_full": "",
    "es_description_full": "",
    "highlights": [],
    "es_title_optimized": "",
    "en_title_optimized": "",
    "descr_en": "",
    "descr_es": ""
  },
  "LXER13389": {
    "en_description_full": "",
    "es_description_full": "",
    "highlights": [],
    "es_title_optimized": "",
    "en_title_optimized": "",
    "descr_en": "",
    "descr_es": ""
  },
  "LXER14081": {
    "en_description_full": "",
    "es_description_full": "",
    "highlights": [],
    "es_title_optimized": "",
    "en_title_optimized": "",
    "descr_en": "",
    "descr_es": ""
  },
  "LXER12902": {
    "en_description_full": "",
    "es_description_full": "",
    "highlights": [],
    "es_title_optimized": "",
    "en_title_optimized": "",
    "descr_en": "",
    "descr_es": ""
  },
  "LXHR10962": {
    "en_description_full": "",
    "es_description_full": "",
    "highlights": [],
    "es_title_optimized": "",
    "en_title_optimized": "",
    "descr_en": "",
    "descr_es": ""
  },
  "LXSR13816": {
    "en_description_full": "",
    "es_description_full": "",
    "highlights": [],
    "es_title_optimized": "",
    "en_title_optimized": "",
    "descr_en": "",
    "descr_es": ""
  },
  "LXCR10816": {
    "en_description_full": "",
    "es_description_full": "",
    "highlights": [],
    "es_title_optimized": "",
    "en_title_optimized": "",
    "descr_en": "",
    "descr_es": ""
  },
  "LXER13113": {
    "en_description_full": "",
    "es_description_full": "",
    "highlights": [],
    "es_title_optimized": "",
    "en_title_optimized": "",
    "descr_en": "",
    "descr_es": ""
  },
  "LXHR13180": {
    "en_description_full": "",
    "es_description_full": "",
    "highlights": [],
    "es_title_optimized": "",
    "en_title_optimized": "",
    "descr_en": "",
    "descr_es": ""
  },
  "LXCR10401": {
    "en_description_full": "",
    "es_description_full": "",
    "highlights": [],
    "es_title_optimized": "",
    "en_title_optimized": "",
    "descr_en": "",
    "descr_es": ""
  },
  "LXER13744": {
    "en_description_full": "",
    "es_description_full": "",
    "highlights": [],
    "es_title_optimized": "",
    "en_title_optimized": "",
    "descr_en": "",
    "descr_es": ""
  },
  "LXHR13578": {
    "en_description_full": "",
    "es_description_full": "",
    "highlights": [],
    "es_title_optimized": "",
    "en_title_optimized": "",
    "descr_en": "",
    "descr_es": ""
  },
  "LXCR13245": {
    "en_description_full": "",
    "es_description_full": "",
    "highlights": [],
    "es_title_optimized": "",
    "en_title_optimized": "",
    "descr_en": "",
    "descr_es": ""
  },
  "LXER12922": {
    "en_description_full": "",
    "es_description_full": "",
    "highlights": [],
    "es_title_optimized": "",
    "en_title_optimized": "",
    "descr_en": "",
    "descr_es": ""
  },
  "LXR13403": {
    "en_description_full": "",
    "es_description_full": "",
    "highlights": [],
    "es_title_optimized": "",
    "en_title_optimized": "",
    "descr_en": "",
    "descr_es": ""
  }
}